DNAPROT_package/DNAPROT_analysis.py
DNAPROT_package/__init__.py
DNAPROT-0.1.0.dist-info/LICENSE.txt
DNAPROT-0.1.0.dist-info/METADATA
DNAPROT-0.1.0.dist-info/WHEEL
DNAPROT-0.1.0.dist-info/top_level.txt
DNAPROT-0.1.0.dist-info/RECORD
