Metadata-Version: 2.1
Name: DNAPROT
Version: 0.1.0
Summary: A DNA and protein analyser tool
Home-page: https://github.com/juan-salafranca/Project-Dna
Author: Juan Salafranca, Marie Van Rossum
Author-email: juan.salafrancamartinez@epfl.ch , marie.vanrossum@epfl.ch
Classifier: Programming Language :: Python :: 3
Classifier: License :: OSI Approved :: MIT License
Classifier: Operating System :: OS Independent
Requires-Python: >=3.6
License-File: LICENSE.txt
Requires-Dist: pandas
Requires-Dist: openpyxl
